{"nodes": [{"id": "watcher_test_go", "label": "watcher_test.go", "file_type": "code", "source_file": "watcher_test.go", "source_location": "L1"}, {"id": "watcher_test_initwatcherwithoptions", "label": "initWatcherWithOptions()", "file_type": "code", "source_file": "watcher_test.go", "source_location": "L16"}, {"id": "watcher_test_initwatcher", "label": "initWatcher()", "file_type": "code", "source_file": "watcher_test.go", "source_location": "L42"}, {"id": "watcher_test_testwatcher", "label": "TestWatcher()", "file_type": "code", "source_file": "watcher_test.go", "source_location": "L46"}, {"id": "watcher_test_testwatcherwithingnoreselffalse", "label": "TestWatcherWithIngnoreSelfFalse()", "file_type": "code", "source_file": "watcher_test.go", "source_location": "L56"}, {"id": "watcher_test_testwatcherwithignoreselftrue", "label": "TestWatcherWithIgnoreSelfTrue()", "file_type": "code", "source_file": "watcher_test.go", "source_location": "L75"}, {"id": "watcher_test_testupdate", "label": "TestUpdate()", "file_type": "code", "source_file": "watcher_test.go", "source_location": "L91"}, {"id": "watcher_test_testupdateforaddpolicy", "label": "TestUpdateForAddPolicy()", "file_type": "code", "source_file": "watcher_test.go", "source_location": "L110"}, {"id": "watcher_test_testupdateforremovepolicy", "label": "TestUpdateForRemovePolicy()", "file_type": "code", "source_file": "watcher_test.go", "source_location": "L132"}, {"id": "watcher_test_testupdateforremovefilteredpolicy", "label": "TestUpdateForRemoveFilteredPolicy()", "file_type": "code", "source_file": "watcher_test.go", "source_location": "L154"}, {"id": "watcher_test_testupdatesavepolicy", "label": "TestUpdateSavePolicy()", "file_type": "code", "source_file": "watcher_test.go", "source_location": "L176"}, {"id": "watcher_test_testupdateforaddpolicies", "label": "TestUpdateForAddPolicies()", "file_type": "code", "source_file": "watcher_test.go", "source_location": "L198"}, {"id": "watcher_test_testupdateforremovepolicies", "label": "TestUpdateForRemovePolicies()", "file_type": "code", "source_file": "watcher_test.go", "source_location": "L227"}, {"id": "watcher_test_testupdateforupdatepolicy", "label": "TestUpdateForUpdatePolicy()", "file_type": "code", "source_file": "watcher_test.go", "source_location": "L256"}, {"id": "watcher_test_testupdateforupdatepolicies", "label": "TestUpdateForUpdatePolicies()", "file_type": "code", "source_file": "watcher_test.go", "source_location": "L279"}], "edges": [{"source": "watcher_test_go", "target": "json", "relation": "imports_from", "confidence": "EXTRACTED", "source_file": "watcher_test.go", "source_location": "L4", "weight": 1.0}, {"source": "watcher_test_go", "target": "fmt", "relation": "imports_from", "confidence": "EXTRACTED", "source_file": "watcher_test.go", "source_location": "L5", "weight": 1.0}, {"source": "watcher_test_go", "target": "uuid", "relation": "imports_from", "confidence": "EXTRACTED", "source_file": "watcher_test.go", "source_location": "L6", "weight": 1.0}, {"source": "watcher_test_go", "target": "reflect", "relation": "imports_from", "confidence": "EXTRACTED", "source_file": "watcher_test.go", "source_location": "L7", "weight": 1.0}, {"source": "watcher_test_go", "target": "testing", "relation": "imports_from", "confidence": "EXTRACTED", "source_file": "watcher_test.go", "source_location": "L8", "weight": 1.0}, {"source": "watcher_test_go", "target": "time", "relation": "imports_from", "confidence": "EXTRACTED", "source_file": "watcher_test.go", "source_location": "L9", "weight": 1.0}, {"source": "watcher_test_go", "target": "v2", "relation": "imports_from", "confidence": "EXTRACTED", "source_file": "watcher_test.go", "source_location": "L11", "weight": 1.0}, {"source": "watcher_test_go", "target": "persist", "relation": "imports_from", "confidence": "EXTRACTED", "source_file": "watcher_test.go", "source_location": "L12", "weight": 1.0}, {"source": "watcher_test_go", "target": "v2", "relation": "imports_from", "confidence": "EXTRACTED", "source_file": "watcher_test.go", "source_location": "L13", "weight": 1.0}, {"source": "watcher_test_go", "target": "watcher_test_initwatcherwithoptions", "relation": "contains", "confidence": "EXTRACTED", "source_file": "watcher_test.go", "source_location": "L16", "weight": 1.0}, {"source": "watcher_test_go", "target": "watcher_test_initwatcher", "relation": "contains", "confidence": "EXTRACTED", "source_file": "watcher_test.go", "source_location": "L42", "weight": 1.0}, {"source": "watcher_test_go", "target": "watcher_test_testwatcher", "relation": "contains", "confidence": "EXTRACTED", "source_file": "watcher_test.go", "source_location": "L46", "weight": 1.0}, {"source": "watcher_test_go", "target": "watcher_test_testwatcherwithingnoreselffalse", "relation": "contains", "confidence": "EXTRACTED", "source_file": "watcher_test.go", "source_location": "L56", "weight": 1.0}, {"source": "watcher_test_go", "target": "watcher_test_testwatcherwithignoreselftrue", "relation": "contains", "confidence": "EXTRACTED", "source_file": "watcher_test.go", "source_location": "L75", "weight": 1.0}, {"source": "watcher_test_go", "target": "watcher_test_testupdate", "relation": "contains", "confidence": "EXTRACTED", "source_file": "watcher_test.go", "source_location": "L91", "weight": 1.0}, {"source": "watcher_test_go", "target": "watcher_test_testupdateforaddpolicy", "relation": "contains", "confidence": "EXTRACTED", "source_file": "watcher_test.go", "source_location": "L110", "weight": 1.0}, {"source": "watcher_test_go", "target": "watcher_test_testupdateforremovepolicy", "relation": "contains", "confidence": "EXTRACTED", "source_file": "watcher_test.go", "source_location": "L132", "weight": 1.0}, {"source": "watcher_test_go", "target": "watcher_test_testupdateforremovefilteredpolicy", "relation": "contains", "confidence": "EXTRACTED", "source_file": "watcher_test.go", "source_location": "L154", "weight": 1.0}, {"source": "watcher_test_go", "target": "watcher_test_testupdatesavepolicy", "relation": "contains", "confidence": "EXTRACTED", "source_file": "watcher_test.go", "source_location": "L176", "weight": 1.0}, {"source": "watcher_test_go", "target": "watcher_test_testupdateforaddpolicies", "relation": "contains", "confidence": "EXTRACTED", "source_file": "watcher_test.go", "source_location": "L198", "weight": 1.0}, {"source": "watcher_test_go", "target": "watcher_test_testupdateforremovepolicies", "relation": "contains", "confidence": "EXTRACTED", "source_file": "watcher_test.go", "source_location": "L227", "weight": 1.0}, {"source": "watcher_test_go", "target": "watcher_test_testupdateforupdatepolicy", "relation": "contains", "confidence": "EXTRACTED", "source_file": "watcher_test.go", "source_location": "L256", "weight": 1.0}, {"source": "watcher_test_go", "target": "watcher_test_testupdateforupdatepolicies", "relation": "contains", "confidence": "EXTRACTED", "source_file": "watcher_test.go", "source_location": "L279", "weight": 1.0}, {"source": "watcher_test_initwatcher", "target": "watcher_test_initwatcherwithoptions", "relation": "calls", "confidence": "EXTRACTED", "source_file": "watcher_test.go", "source_location": "L43", "weight": 1.0}, {"source": "watcher_test_testwatcher", "target": "watcher_test_initwatcher", "relation": "calls", "confidence": "EXTRACTED", "source_file": "watcher_test.go", "source_location": "L47", "weight": 1.0}, {"source": "watcher_test_testwatcherwithingnoreselffalse", "target": "watcher_test_initwatcherwithoptions", "relation": "calls", "confidence": "EXTRACTED", "source_file": "watcher_test.go", "source_location": "L60", "weight": 1.0}, {"source": "watcher_test_testwatcherwithignoreselftrue", "target": "watcher_test_initwatcherwithoptions", "relation": "calls", "confidence": "EXTRACTED", "source_file": "watcher_test.go", "source_location": "L79", "weight": 1.0}, {"source": "watcher_test_testupdate", "target": "watcher_test_initwatcher", "relation": "calls", "confidence": "EXTRACTED", "source_file": "watcher_test.go", "source_location": "L92", "weight": 1.0}, {"source": "watcher_test_testupdateforaddpolicy", "target": "watcher_test_initwatcherwithoptions", "relation": "calls", "confidence": "EXTRACTED", "source_file": "watcher_test.go", "source_location": "L114", "weight": 1.0}, {"source": "watcher_test_testupdateforremovepolicy", "target": "watcher_test_initwatcherwithoptions", "relation": "calls", "confidence": "EXTRACTED", "source_file": "watcher_test.go", "source_location": "L136", "weight": 1.0}, {"source": "watcher_test_testupdateforremovefilteredpolicy", "target": "watcher_test_initwatcherwithoptions", "relation": "calls", "confidence": "EXTRACTED", "source_file": "watcher_test.go", "source_location": "L158", "weight": 1.0}, {"source": "watcher_test_testupdatesavepolicy", "target": "watcher_test_initwatcherwithoptions", "relation": "calls", "confidence": "EXTRACTED", "source_file": "watcher_test.go", "source_location": "L180", "weight": 1.0}, {"source": "watcher_test_testupdateforaddpolicies", "target": "watcher_test_initwatcherwithoptions", "relation": "calls", "confidence": "EXTRACTED", "source_file": "watcher_test.go", "source_location": "L209", "weight": 1.0}, {"source": "watcher_test_testupdateforremovepolicies", "target": "watcher_test_initwatcherwithoptions", "relation": "calls", "confidence": "EXTRACTED", "source_file": "watcher_test.go", "source_location": "L238", "weight": 1.0}, {"source": "watcher_test_testupdateforupdatepolicy", "target": "watcher_test_initwatcherwithoptions", "relation": "calls", "confidence": "EXTRACTED", "source_file": "watcher_test.go", "source_location": "L260", "weight": 1.0}, {"source": "watcher_test_testupdateforupdatepolicies", "target": "watcher_test_initwatcherwithoptions", "relation": "calls", "confidence": "EXTRACTED", "source_file": "watcher_test.go", "source_location": "L283", "weight": 1.0}], "raw_calls": [{"caller_nid": "watcher_test_initwatcherwithoptions", "callee": "len", "source_file": "watcher_test.go", "source_location": "L21"}, {"caller_nid": "watcher_test_initwatcherwithoptions", "callee": "NewWatcherWithCluster", "source_file": "watcher_test.go", "source_location": "L22"}, {"caller_nid": "watcher_test_initwatcherwithoptions", "callee": "NewWatcher", "source_file": "watcher_test.go", "source_location": "L24"}, {"caller_nid": "watcher_test_initwatcherwithoptions", "callee": "Fatalf", "source_file": "watcher_test.go", "source_location": "L27"}, {"caller_nid": "watcher_test_initwatcherwithoptions", "callee": "NewEnforcer", "source_file": "watcher_test.go", "source_location": "L30"}, {"caller_nid": "watcher_test_initwatcherwithoptions", "callee": "Fatalf", "source_file": "watcher_test.go", "source_location": "L32"}, {"caller_nid": "watcher_test_initwatcherwithoptions", "callee": "SetWatcher", "source_file": "watcher_test.go", "source_location": "L34"}, {"caller_nid": "watcher_test_initwatcherwithoptions", "callee": "SetUpdateCallback", "source_file": "watcher_test.go", "source_location": "L35"}, {"caller_nid": "watcher_test_initwatcherwithoptions", "callee": "Log", "source_file": "watcher_test.go", "source_location": "L36"}, {"caller_nid": "watcher_test_initwatcherwithoptions", "callee": "DefaultUpdateCallback", "source_file": "watcher_test.go", "source_location": "L37"}, {"caller_nid": "watcher_test_testwatcher", "callee": "SetUpdateCallback", "source_file": "watcher_test.go", "source_location": "L48"}, {"caller_nid": "watcher_test_testwatcher", "callee": "Println", "source_file": "watcher_test.go", "source_location": "L49"}, {"caller_nid": "watcher_test_testwatcher", "callee": "Update", "source_file": "watcher_test.go", "source_location": "L51"}, {"caller_nid": "watcher_test_testwatcher", "callee": "Close", "source_file": "watcher_test.go", "source_location": "L52"}, {"caller_nid": "watcher_test_testwatcher", "callee": "Sleep", "source_file": "watcher_test.go", "source_location": "L53"}, {"caller_nid": "watcher_test_testwatcherwithingnoreselffalse", "callee": "String", "source_file": "watcher_test.go", "source_location": "L58"}, {"caller_nid": "watcher_test_testwatcherwithingnoreselffalse", "callee": "New", "source_file": "watcher_test.go", "source_location": "L58"}, {"caller_nid": "watcher_test_testwatcherwithingnoreselffalse", "callee": "SetUpdateCallback", "source_file": "watcher_test.go", "source_location": "L61"}, {"caller_nid": "watcher_test_testwatcherwithingnoreselffalse", "callee": "Unmarshal", "source_file": "watcher_test.go", "source_location": "L63"}, {"caller_nid": "watcher_test_testwatcherwithingnoreselffalse", "callee": "Fatalf", "source_file": "watcher_test.go", "source_location": "L65"}, {"caller_nid": "watcher_test_testwatcherwithingnoreselffalse", "callee": "Update", "source_file": "watcher_test.go", "source_location": "L69"}, {"caller_nid": "watcher_test_testwatcherwithingnoreselffalse", "callee": "Sleep", "source_file": "watcher_test.go", "source_location": "L70"}, {"caller_nid": "watcher_test_testwatcherwithingnoreselffalse", "callee": "Close", "source_file": "watcher_test.go", "source_location": "L71"}, {"caller_nid": "watcher_test_testwatcherwithingnoreselffalse", "callee": "Sleep", "source_file": "watcher_test.go", "source_location": "L72"}, {"caller_nid": "watcher_test_testwatcherwithignoreselftrue", "callee": "SetUpdateCallback", "source_file": "watcher_test.go", "source_location": "L81"}, {"caller_nid": "watcher_test_testwatcherwithignoreselftrue", "callee": "Fatalf", "source_file": "watcher_test.go", "source_location": "L82"}, {"caller_nid": "watcher_test_testwatcherwithignoreselftrue", "callee": "Update", "source_file": "watcher_test.go", "source_location": "L85"}, {"caller_nid": "watcher_test_testwatcherwithignoreselftrue", "callee": "Sleep", "source_file": "watcher_test.go", "source_location": "L86"}, {"caller_nid": "watcher_test_testwatcherwithignoreselftrue", "callee": "Close", "source_file": "watcher_test.go", "source_location": "L87"}, {"caller_nid": "watcher_test_testwatcherwithignoreselftrue", "callee": "Sleep", "source_file": "watcher_test.go", "source_location": "L88"}, {"caller_nid": "watcher_test_testupdate", "callee": "SetUpdateCallback", "source_file": "watcher_test.go", "source_location": "L93"}, {"caller_nid": "watcher_test_testupdate", "callee": "UnmarshalBinary", "source_file": "watcher_test.go", "source_location": "L96"}, {"caller_nid": "watcher_test_testupdate", "callee": "Error", "source_file": "watcher_test.go", "source_location": "L98"}, {"caller_nid": "watcher_test_testupdate", "callee": "Errorf", "source_file": "watcher_test.go", "source_location": "L102"}, {"caller_nid": "watcher_test_testupdate", "callee": "Update", "source_file": "watcher_test.go", "source_location": "L105"}, {"caller_nid": "watcher_test_testupdate", "callee": "Close", "source_file": "watcher_test.go", "source_location": "L106"}, {"caller_nid": "watcher_test_testupdate", "callee": "Sleep", "source_file": "watcher_test.go", "source_location": "L107"}, {"caller_nid": "watcher_test_testupdateforaddpolicy", "callee": "Sleep", "source_file": "watcher_test.go", "source_location": "L117"}, {"caller_nid": "watcher_test_testupdateforaddpolicy", "callee": "AddPolicy", "source_file": "watcher_test.go", "source_location": "L118"}, {"caller_nid": "watcher_test_testupdateforaddpolicy", "callee": "Sleep", "source_file": "watcher_test.go", "source_location": "L119"}, {"caller_nid": "watcher_test_testupdateforaddpolicy", "callee": "DeepEqual", "source_file": "watcher_test.go", "source_location": "L120"}, {"caller_nid": "watcher_test_testupdateforaddpolicy", "callee": "GetPolicy", "source_file": "watcher_test.go", "source_location": "L120"}, {"caller_nid": "watcher_test_testupdateforaddpolicy", "callee": "GetPolicy", "source_file": "watcher_test.go", "source_location": "L120"}, {"caller_nid": "watcher_test_testupdateforaddpolicy", "callee": "Log", "source_file": "watcher_test.go", "source_location": "L121"}, {"caller_nid": "watcher_test_testupdateforaddpolicy", "callee": "Log", "source_file": "watcher_test.go", "source_location": "L122"}, {"caller_nid": "watcher_test_testupdateforaddpolicy", "callee": "GetPolicy", "source_file": "watcher_test.go", "source_location": "L122"}, {"caller_nid": "watcher_test_testupdateforaddpolicy", "callee": "Log", "source_file": "watcher_test.go", "source_location": "L123"}, {"caller_nid": "watcher_test_testupdateforaddpolicy", "callee": "GetPolicy", "source_file": "watcher_test.go", "source_location": "L123"}, {"caller_nid": "watcher_test_testupdateforaddpolicy", "callee": "Error", "source_file": "watcher_test.go", "source_location": "L124"}, {"caller_nid": "watcher_test_testupdateforaddpolicy", "callee": "Close", "source_file": "watcher_test.go", "source_location": "L127"}, {"caller_nid": "watcher_test_testupdateforaddpolicy", "callee": "Close", "source_file": "watcher_test.go", "source_location": "L128"}, {"caller_nid": "watcher_test_testupdateforaddpolicy", "callee": "Sleep", "source_file": "watcher_test.go", "source_location": "L129"}, {"caller_nid": "watcher_test_testupdateforremovepolicy", "callee": "Sleep", "source_file": "watcher_test.go", "source_location": "L139"}, {"caller_nid": "watcher_test_testupdateforremovepolicy", "callee": "RemovePolicy", "source_file": "watcher_test.go", "source_location": "L140"}, {"caller_nid": "watcher_test_testupdateforremovepolicy", "callee": "Sleep", "source_file": "watcher_test.go", "source_location": "L141"}, {"caller_nid": "watcher_test_testupdateforremovepolicy", "callee": "DeepEqual", "source_file": "watcher_test.go", "source_location": "L142"}, {"caller_nid": "watcher_test_testupdateforremovepolicy", "callee": "GetPolicy", "source_file": "watcher_test.go", "source_location": "L142"}, {"caller_nid": "watcher_test_testupdateforremovepolicy", "callee": "GetPolicy", "source_file": "watcher_test.go", "source_location": "L142"}, {"caller_nid": "watcher_test_testupdateforremovepolicy", "callee": "Log", "source_file": "watcher_test.go", "source_location": "L143"}, {"caller_nid": "watcher_test_testupdateforremovepolicy", "callee": "Log", "source_file": "watcher_test.go", "source_location": "L144"}, {"caller_nid": "watcher_test_testupdateforremovepolicy", "callee": "GetPolicy", "source_file": "watcher_test.go", "source_location": "L144"}, {"caller_nid": "watcher_test_testupdateforremovepolicy", "callee": "Log", "source_file": "watcher_test.go", "source_location": "L145"}, {"caller_nid": "watcher_test_testupdateforremovepolicy", "callee": "GetPolicy", "source_file": "watcher_test.go", "source_location": "L145"}, {"caller_nid": "watcher_test_testupdateforremovepolicy", "callee": "Error", "source_file": "watcher_test.go", "source_location": "L146"}, {"caller_nid": "watcher_test_testupdateforremovepolicy", "callee": "Close", "source_file": "watcher_test.go", "source_location": "L149"}, {"caller_nid": "watcher_test_testupdateforremovepolicy", "callee": "Close", "source_file": "watcher_test.go", "source_location": "L150"}, {"caller_nid": "watcher_test_testupdateforremovepolicy", "callee": "Sleep", "source_file": "watcher_test.go", "source_location": "L151"}, {"caller_nid": "watcher_test_testupdateforremovefilteredpolicy", "callee": "Sleep", "source_file": "watcher_test.go", "source_location": "L161"}, {"caller_nid": "watcher_test_testupdateforremovefilteredpolicy", "callee": "RemoveFilteredPolicy", "source_file": "watcher_test.go", "source_location": "L162"}, {"caller_nid": "watcher_test_testupdateforremovefilteredpolicy", "callee": "Sleep", "source_file": "watcher_test.go", "source_location": "L163"}, {"caller_nid": "watcher_test_testupdateforremovefilteredpolicy", "callee": "DeepEqual", "source_file": "watcher_test.go", "source_location": "L164"}, {"caller_nid": "watcher_test_testupdateforremovefilteredpolicy", "callee": "GetPolicy", "source_file": "watcher_test.go", "source_location": "L164"}, {"caller_nid": "watcher_test_testupdateforremovefilteredpolicy", "callee": "GetPolicy", "source_file": "watcher_test.go", "source_location": "L164"}, {"caller_nid": "watcher_test_testupdateforremovefilteredpolicy", "callee": "Log", "source_file": "watcher_test.go", "source_location": "L165"}, {"caller_nid": "watcher_test_testupdateforremovefilteredpolicy", "callee": "Log", "source_file": "watcher_test.go", "source_location": "L166"}, {"caller_nid": "watcher_test_testupdateforremovefilteredpolicy", "callee": "GetPolicy", "source_file": "watcher_test.go", "source_location": "L166"}, {"caller_nid": "watcher_test_testupdateforremovefilteredpolicy", "callee": "Log", "source_file": "watcher_test.go", "source_location": "L167"}, {"caller_nid": "watcher_test_testupdateforremovefilteredpolicy", "callee": "GetPolicy", "source_file": "watcher_test.go", "source_location": "L167"}, {"caller_nid": "watcher_test_testupdateforremovefilteredpolicy", "callee": "Error", "source_file": "watcher_test.go", "source_location": "L168"}, {"caller_nid": "watcher_test_testupdateforremovefilteredpolicy", "callee": "Close", "source_file": "watcher_test.go", "source_location": "L171"}, {"caller_nid": "watcher_test_testupdateforremovefilteredpolicy", "callee": "Close", "source_file": "watcher_test.go", "source_location": "L172"}, {"caller_nid": "watcher_test_testupdateforremovefilteredpolicy", "callee": "Sleep", "source_file": "watcher_test.go", "source_location": "L173"}, {"caller_nid": "watcher_test_testupdatesavepolicy", "callee": "Sleep", "source_file": "watcher_test.go", "source_location": "L183"}, {"caller_nid": "watcher_test_testupdatesavepolicy", "callee": "SavePolicy", "source_file": "watcher_test.go", "source_location": "L184"}, {"caller_nid": "watcher_test_testupdatesavepolicy", "callee": "Sleep", "source_file": "watcher_test.go", "source_location": "L185"}, {"caller_nid": "watcher_test_testupdatesavepolicy", "callee": "DeepEqual", "source_file": "watcher_test.go", "source_location": "L186"}, {"caller_nid": "watcher_test_testupdatesavepolicy", "callee": "GetPolicy", "source_file": "watcher_test.go", "source_location": "L186"}, {"caller_nid": "watcher_test_testupdatesavepolicy", "callee": "GetPolicy", "source_file": "watcher_test.go", "source_location": "L186"}, {"caller_nid": "watcher_test_testupdatesavepolicy", "callee": "Log", "source_file": "watcher_test.go", "source_location": "L187"}, {"caller_nid": "watcher_test_testupdatesavepolicy", "callee": "Log", "source_file": "watcher_test.go", "source_location": "L188"}, {"caller_nid": "watcher_test_testupdatesavepolicy", "callee": "GetPolicy", "source_file": "watcher_test.go", "source_location": "L188"}, {"caller_nid": "watcher_test_testupdatesavepolicy", "callee": "Log", "source_file": "watcher_test.go", "source_location": "L189"}, {"caller_nid": "watcher_test_testupdatesavepolicy", "callee": "GetPolicy", "source_file": "watcher_test.go", "source_location": "L189"}, {"caller_nid": "watcher_test_testupdatesavepolicy", "callee": "Error", "source_file": "watcher_test.go", "source_location": "L190"}, {"caller_nid": "watcher_test_testupdatesavepolicy", "callee": "Close", "source_file": "watcher_test.go", "source_location": "L193"}, {"caller_nid": "watcher_test_testupdatesavepolicy", "callee": "Close", "source_file": "watcher_test.go", "source_location": "L194"}, {"caller_nid": "watcher_test_testupdatesavepolicy", "callee": "Sleep", "source_file": "watcher_test.go", "source_location": "L195"}, {"caller_nid": "watcher_test_testupdateforaddpolicies", "callee": "Sleep", "source_file": "watcher_test.go", "source_location": "L212"}, {"caller_nid": "watcher_test_testupdateforaddpolicies", "callee": "AddPolicies", "source_file": "watcher_test.go", "source_location": "L213"}, {"caller_nid": "watcher_test_testupdateforaddpolicies", "callee": "Sleep", "source_file": "watcher_test.go", "source_location": "L214"}, {"caller_nid": "watcher_test_testupdateforaddpolicies", "callee": "DeepEqual", "source_file": "watcher_test.go", "source_location": "L215"}, {"caller_nid": "watcher_test_testupdateforaddpolicies", "callee": "GetPolicy", "source_file": "watcher_test.go", "source_location": "L215"}, {"caller_nid": "watcher_test_testupdateforaddpolicies", "callee": "GetPolicy", "source_file": "watcher_test.go", "source_location": "L215"}, {"caller_nid": "watcher_test_testupdateforaddpolicies", "callee": "Log", "source_file": "watcher_test.go", "source_location": "L216"}, {"caller_nid": "watcher_test_testupdateforaddpolicies", "callee": "Log", "source_file": "watcher_test.go", "source_location": "L217"}, {"caller_nid": "watcher_test_testupdateforaddpolicies", "callee": "GetPolicy", "source_file": "watcher_test.go", "source_location": "L217"}, {"caller_nid": "watcher_test_testupdateforaddpolicies", "callee": "Log", "source_file": "watcher_test.go", "source_location": "L218"}, {"caller_nid": "watcher_test_testupdateforaddpolicies", "callee": "GetPolicy", "source_file": "watcher_test.go", "source_location": "L218"}, {"caller_nid": "watcher_test_testupdateforaddpolicies", "callee": "Error", "source_file": "watcher_test.go", "source_location": "L219"}, {"caller_nid": "watcher_test_testupdateforaddpolicies", "callee": "Close", "source_file": "watcher_test.go", "source_location": "L222"}, {"caller_nid": "watcher_test_testupdateforaddpolicies", "callee": "Close", "source_file": "watcher_test.go", "source_location": "L223"}, {"caller_nid": "watcher_test_testupdateforaddpolicies", "callee": "Sleep", "source_file": "watcher_test.go", "source_location": "L224"}, {"caller_nid": "watcher_test_testupdateforremovepolicies", "callee": "Sleep", "source_file": "watcher_test.go", "source_location": "L241"}, {"caller_nid": "watcher_test_testupdateforremovepolicies", "callee": "RemovePolicies", "source_file": "watcher_test.go", "source_location": "L242"}, {"caller_nid": "watcher_test_testupdateforremovepolicies", "callee": "Sleep", "source_file": "watcher_test.go", "source_location": "L243"}, {"caller_nid": "watcher_test_testupdateforremovepolicies", "callee": "DeepEqual", "source_file": "watcher_test.go", "source_location": "L244"}, {"caller_nid": "watcher_test_testupdateforremovepolicies", "callee": "GetPolicy", "source_file": "watcher_test.go", "source_location": "L244"}, {"caller_nid": "watcher_test_testupdateforremovepolicies", "callee": "GetPolicy", "source_file": "watcher_test.go", "source_location": "L244"}, {"caller_nid": "watcher_test_testupdateforremovepolicies", "callee": "Log", "source_file": "watcher_test.go", "source_location": "L245"}, {"caller_nid": "watcher_test_testupdateforremovepolicies", "callee": "Log", "source_file": "watcher_test.go", "source_location": "L246"}, {"caller_nid": "watcher_test_testupdateforremovepolicies", "callee": "GetPolicy", "source_file": "watcher_test.go", "source_location": "L246"}, {"caller_nid": "watcher_test_testupdateforremovepolicies", "callee": "Log", "source_file": "watcher_test.go", "source_location": "L247"}, {"caller_nid": "watcher_test_testupdateforremovepolicies", "callee": "GetPolicy", "source_file": "watcher_test.go", "source_location": "L247"}, {"caller_nid": "watcher_test_testupdateforremovepolicies", "callee": "Error", "source_file": "watcher_test.go", "source_location": "L248"}, {"caller_nid": "watcher_test_testupdateforremovepolicies", "callee": "Close", "source_file": "watcher_test.go", "source_location": "L251"}, {"caller_nid": "watcher_test_testupdateforremovepolicies", "callee": "Close", "source_file": "watcher_test.go", "source_location": "L252"}, {"caller_nid": "watcher_test_testupdateforremovepolicies", "callee": "Sleep", "source_file": "watcher_test.go", "source_location": "L253"}, {"caller_nid": "watcher_test_testupdateforupdatepolicy", "callee": "Sleep", "source_file": "watcher_test.go", "source_location": "L263"}, {"caller_nid": "watcher_test_testupdateforupdatepolicy", "callee": "UpdatePolicy", "source_file": "watcher_test.go", "source_location": "L264"}, {"caller_nid": "watcher_test_testupdateforupdatepolicy", "callee": "Sleep", "source_file": "watcher_test.go", "source_location": "L266"}, {"caller_nid": "watcher_test_testupdateforupdatepolicy", "callee": "DeepEqual", "source_file": "watcher_test.go", "source_location": "L267"}, {"caller_nid": "watcher_test_testupdateforupdatepolicy", "callee": "GetPolicy", "source_file": "watcher_test.go", "source_location": "L267"}, {"caller_nid": "watcher_test_testupdateforupdatepolicy", "callee": "GetPolicy", "source_file": "watcher_test.go", "source_location": "L267"}, {"caller_nid": "watcher_test_testupdateforupdatepolicy", "callee": "Log", "source_file": "watcher_test.go", "source_location": "L268"}, {"caller_nid": "watcher_test_testupdateforupdatepolicy", "callee": "Log", "source_file": "watcher_test.go", "source_location": "L269"}, {"caller_nid": "watcher_test_testupdateforupdatepolicy", "callee": "GetPolicy", "source_file": "watcher_test.go", "source_location": "L269"}, {"caller_nid": "watcher_test_testupdateforupdatepolicy", "callee": "Log", "source_file": "watcher_test.go", "source_location": "L270"}, {"caller_nid": "watcher_test_testupdateforupdatepolicy", "callee": "GetPolicy", "source_file": "watcher_test.go", "source_location": "L270"}, {"caller_nid": "watcher_test_testupdateforupdatepolicy", "callee": "Error", "source_file": "watcher_test.go", "source_location": "L271"}, {"caller_nid": "watcher_test_testupdateforupdatepolicy", "callee": "Close", "source_file": "watcher_test.go", "source_location": "L274"}, {"caller_nid": "watcher_test_testupdateforupdatepolicy", "callee": "Close", "source_file": "watcher_test.go", "source_location": "L275"}, {"caller_nid": "watcher_test_testupdateforupdatepolicy", "callee": "Sleep", "source_file": "watcher_test.go", "source_location": "L276"}, {"caller_nid": "watcher_test_testupdateforupdatepolicies", "callee": "Sleep", "source_file": "watcher_test.go", "source_location": "L286"}, {"caller_nid": "watcher_test_testupdateforupdatepolicies", "callee": "UpdatePolicies", "source_file": "watcher_test.go", "source_location": "L287"}, {"caller_nid": "watcher_test_testupdateforupdatepolicies", "callee": "Sleep", "source_file": "watcher_test.go", "source_location": "L289"}, {"caller_nid": "watcher_test_testupdateforupdatepolicies", "callee": "DeepEqual", "source_file": "watcher_test.go", "source_location": "L290"}, {"caller_nid": "watcher_test_testupdateforupdatepolicies", "callee": "GetPolicy", "source_file": "watcher_test.go", "source_location": "L290"}, {"caller_nid": "watcher_test_testupdateforupdatepolicies", "callee": "GetPolicy", "source_file": "watcher_test.go", "source_location": "L290"}, {"caller_nid": "watcher_test_testupdateforupdatepolicies", "callee": "Log", "source_file": "watcher_test.go", "source_location": "L291"}, {"caller_nid": "watcher_test_testupdateforupdatepolicies", "callee": "Log", "source_file": "watcher_test.go", "source_location": "L292"}, {"caller_nid": "watcher_test_testupdateforupdatepolicies", "callee": "GetPolicy", "source_file": "watcher_test.go", "source_location": "L292"}, {"caller_nid": "watcher_test_testupdateforupdatepolicies", "callee": "Log", "source_file": "watcher_test.go", "source_location": "L293"}, {"caller_nid": "watcher_test_testupdateforupdatepolicies", "callee": "GetPolicy", "source_file": "watcher_test.go", "source_location": "L293"}, {"caller_nid": "watcher_test_testupdateforupdatepolicies", "callee": "Error", "source_file": "watcher_test.go", "source_location": "L294"}, {"caller_nid": "watcher_test_testupdateforupdatepolicies", "callee": "Close", "source_file": "watcher_test.go", "source_location": "L297"}, {"caller_nid": "watcher_test_testupdateforupdatepolicies", "callee": "Close", "source_file": "watcher_test.go", "source_location": "L298"}, {"caller_nid": "watcher_test_testupdateforupdatepolicies", "callee": "Sleep", "source_file": "watcher_test.go", "source_location": "L299"}]}